llm_github/__init__.py
llm_github/core.py
llm_github/execute.py
llm_github-0.0.2.dist-info/LICENSE
llm_github-0.0.2.dist-info/METADATA
llm_github-0.0.2.dist-info/WHEEL
llm_github-0.0.2.dist-info/RECORD
