Metadata-Version: 2.1
Name: llm_github
Version: 0.0.2
Summary: Tools for extracting knowledge from GitHub issues, PR comments, etc.
Home-page: https://github.com/turbomam/llm-github
Author: Mark Andrew Miller
Author-email: mamillerpa@gmail.com
Requires-Python: >=3.8,<4.0
Classifier: Programming Language :: Python :: 3
Classifier: Programming Language :: Python :: 3.8
Classifier: Programming Language :: Python :: 3.9
Classifier: Programming Language :: Python :: 3.10
Classifier: Programming Language :: Python :: 3.11
Classifier: Programming Language :: Python :: 3.12
Requires-Dist: python-dotenv (>=1.0.1,<2.0.0)
Requires-Dist: requests (>=2.32.3,<3.0.0)
Requires-Dist: requests-cache (>=1.2.1,<2.0.0)
Requires-Dist: typing-extensions (>=4.12.2,<5.0.0)
Project-URL: Documentation, https://turbomam.github.io/llm-github/
Project-URL: Repository, https://github.com/turbomam/llm-github
